vkernelrs-0.1.3.dist-info/METADATA
vkernelrs-0.1.3.dist-info/WHEEL
vkernelrs.libs/libgcc_s-1e52349c.so.1
vkernelrs/__init__.py
vkernelrs/vkernelrs.cpython-38-x86_64-linux-gnu.so
vkernelrs-0.1.3.dist-info/RECORD
