Metadata-Version: 2.3
Name: vkernelrs
Version: 0.1.3
Requires-Dist: cffi
Summary: A Rust library for the vkernel project
Author: Guillaume Boyé
